{"count":104,"ships":[{"mmsi":367513050,"lat":42.380329,"lon":-71.042946,"distance":0.317654,"mmsi_type":1,"level":-28.161266,"count":6895,"ppm":4.918982,"heading":null,"cog":null,"speed":0.000000,"to_bow":10,"to_stern":17,"to_starboard":3,"to_port":5,"shiptype":52,"msg_type":0,"country":"US","status":0,"callsign":"WDG2188","shipname":"VINCENT D. TIBBETTS","destination":"BOSTON","last_signal":0},{"mmsi":367447520,"lat":42.324032,"lon":-70.994347,"distance":3.777312,"mmsi_type":1,"level":-37.657475,"count":1103,"ppm":-1.157407,"heading":156,"cog":155.500000,"speed":28.400000,"to_bow":24,"to_stern":20,"to_starboard":9,"to_port":4,"shiptype":40,"msg_type":0,"country":"US","status":0,"callsign":"WDF4062","shipname":"SALACIA","destination":"XX XXX>?? ???","last_signal":0},{"mmsi":993672306,"lat":42.256966,"lon":-70.918983,"distance":8.978776,"mmsi_type":6,"level":-44.355167,"count":450,"ppm":-0.578704,"heading":null,"cog":null,"speed":null,"to_bow":0,"to_stern":0,"to_starboard":0,"to_port":0,"shiptype":0,"msg_type":0,"country":"US","status":15,"callsign":"","shipname":"10","destination":"","last_signal":1},{"mmsi":366695940,"lat":42.380325,"lon":-71.042374,"distance":0.293299,"mmsi_type":1,"level":-23.845894,"count":6886,"ppm":-1.157407,"heading":null,"cog":1.000000,"speed":0.000000,"to_bow":105,"to_stern":21,"to_starboard":4,"to_port":4,"shiptype":52,"msg_type":0,"country":"US","status":0,"callsign":"WCU4692","shipname":"ZACHERY REINAUER","destination":"BOSTON","last_signal":1},{"mmsi":367784560,"lat":42.313828,"lon":-70.932777,"distance":6.022569,"mmsi_type":1,"level":-43.679356,"count":211,"ppm":0.289352,"heading":325,"cog":327.800018,"speed":25.600000,"to_bow":10,"to_stern":16,"to_starboard":4,"to_port":4,"shiptype":60,"msg_type":0,"country":"US","status":0,"callsign":"WDJ5125","shipname":"CHAMPION","destination":"BOSTON","last_signal":1},{"mmsi":367387420,"lat":42.346203,"lon":-70.834801,"distance":9.144305,"mmsi_type":1,"level":-47.752796,"count":112,"ppm":-1.446759,"heading":49,"cog":31.000000,"speed":11.300000,"to_bow":9,"to_stern":24,"to_starboard":5,"to_port":2,"shiptype":60,"msg_type":0,"country":"US","status":0,"callsign":"WCY8367","shipname":"RUTH E HUGHES","destination":"BOSTON","last_signal":1},{"mmsi":367002660,"lat":42.343224,"lon":-71.031853,"distance":2.147749,"mmsi_type":1,"level":-46.836605,"count":4177,"ppm":-0.578704,"heading":266,"cog":340.399994,"speed":0.100000,"to_bow":20,"to_stern":20,"to_starboard":7,"to_port":7,"shiptype":52,"msg_type":0,"country":"US","status":0,"callsign":"WDJ2691","shipname":"SAPPHIRE COAST","destination":"US^0XX1>0Y2W","last_signal":1},{"mmsi":367627580,"lat":42.283516,"lon":-70.950706,"distance":6.866261,"mmsi_type":1,"level":-43.125885,"count":142,"ppm":-0.578704,"heading":310,"cog":301.100006,"speed":19.700001,"to_bow":11,"to_stern":19,"to_starboard":4,"to_port":3,"shiptype":60,"msg_type":0,"country":"US","status":0,"callsign":"WDH5399","shipname":"MASSACHUSETTS","destination":"HING ROWES FERRY","last_signal":1},{"mmsi":367029020,"lat":42.362747,"lon":-71.031548,"distance":0.987650,"mmsi_type":1,"level":-22.528236,"count":7249,"ppm":-0.868056,"heading":194,"cog":313.200012,"speed":0.100000,"to_bow":0,"to_stern":0,"to_starboard":0,"to_port":0,"shiptype":50,"msg_type":0,"country":"US","status":0,"callsign":"VHF 20","shipname":"BOSTON PILOT MYSTIC","destination":"OWN-SHIP","last_signal":2},{"mmsi":367677670,"lat":42.355560,"lon":-71.049210,"distance":1.515288,"mmsi_type":1,"level":-33.017292,"count":682,"ppm":-1.157407,"heading":286,"cog":247.400009,"speed":0.300000,"to_bow":10,"to_stern":19,"to_starboard":3,"to_port":6,"shiptype":40,"msg_type":0,"country":"US","status":0,"callsign":"WDI2390","shipname":"SANCTUARY","destination":"BOSTON","last_signal":2},{"mmsi":993672298,"lat":42.265625,"lon":-70.930794,"distance":8.251862,"mmsi_type":6,"level":-45.988930,"count":406,"ppm":-0.868056,"heading":null,"cog":null,"speed":null,"to_bow":0,"to_stern":0,"to_starboard":0,"to_port":0,"shiptype":0,"msg_type":0,"country":"US","status":15,"callsign":"","shipname":"1","destination":"","last_signal":2},{"mmsi":367377380,"lat":42.355568,"lon":-71.049683,"distance":1.523065,"mmsi_type":1,"level":-39.257683,"count":6508,"ppm":-4.629630,"heading":277,"cog":20.800001,"speed":0.000000,"to_bow":10,"to_stern":20,"to_starboard":4,"to_port":8,"shiptype":60,"msg_type":0,"country":"US","status":0,"callsign":"WYR2173","shipname":"FREEDOM","destination":"","last_signal":3},{"mmsi":367513020,"lat":42.380405,"lon":-71.042061,"distance":0.281662,"mmsi_type":1,"level":-23.732231,"count":6952,"ppm":-1.157407,"heading":null,"cog":280.399994,"speed":0.000000,"to_bow":21,"to_stern":8,"to_starboard":0,"to_port":10,"shiptype":0,"msg_type":0,"country":"US","status":0,"callsign":"WDG2185","shipname":"HAROLD A. REINAUER","destination":"BOSTON","last_signal":4},{"mmsi":3660610,"lat":42.243275,"lon":-70.836403,"distance":12.038845,"mmsi_type":3,"level":-45.717903,"count":4064,"ppm":-0.578704,"heading":null,"cog":null,"speed":null,"to_bow":null,"to_stern":null,"to_starboard":null,"to_port":null,"shiptype":0,"msg_type":0,"country":"US","status":15,"callsign":"","shipname":"","destination":"","last_signal":4},{"mmsi":993672307,"lat":42.255371,"lon":-70.919777,"distance":9.036873,"mmsi_type":6,"level":-44.495571,"count":457,"ppm":-0.578704,"heading":null,"cog":null,"speed":null,"to_bow":0,"to_stern":0,"to_starboard":0,"to_port":0,"shiptype":0,"msg_type":0,"country":"US","status":15,"callsign":"","shipname":"12","destination":"","last_signal":5},{"mmsi":366999710,"lat":42.369408,"lon":-71.051720,"distance":0.896393,"mmsi_type":1,"level":-20.124643,"count":341,"ppm":-0.868056,"heading":null,"cog":301.300018,"speed":0.000000,"to_bow":14,"to_stern":12,"to_starboard":4,"to_port":2,"shiptype":55,"msg_type":0,"country":"US","status":5,"callsign":"NTGT","shipname":"CG STURGEON","destination":"","last_signal":5},{"mmsi":367551860,"lat":42.351017,"lon":-71.037338,"distance":1.672464,"mmsi_type":1,"level":-35.826817,"count":6724,"ppm":-3.182870,"heading":null,"cog":null,"speed":0.000000,"to_bow":5,"to_stern":14,"to_starboard":4,"to_port":1,"shiptype":99,"msg_type":0,"country":"US","status":4,"callsign":"WDG5937","shipname":"JOCKA","destination":"","last_signal":5},{"mmsi":367782940,"lat":42.302620,"lon":-70.919930,"distance":6.894985,"mmsi_type":1,"level":-47.585346,"count":1461,"ppm":-4.918982,"heading":337,"cog":72.800003,"speed":0.200000,"to_bow":10,"to_stern":16,"to_starboard":4,"to_port":4,"shiptype":60,"msg_type":0,"country":"US","status":0,"callsign":"WDJ4970","shipname":"GLORY","destination":"BOSTON","last_signal":5},{"mmsi":366998170,"lat":42.384533,"lon":-71.059456,"distance":1.092101,"mmsi_type":1,"level":-35.490211,"count":5068,"ppm":-0.868056,"heading":218,"cog":296.100006,"speed":0.000000,"to_bow":21,"to_stern":21,"to_starboard":7,"to_port":7,"shiptype":52,"msg_type":0,"country":"US","status":0,"callsign":"WDJ2403","shipname":"PEARL COAST","destination":"XX XXX>US^0XVG","last_signal":6},{"mmsi":993672297,"lat":42.254642,"lon":-70.984291,"distance":7.805907,"mmsi_type":6,"level":-45.628239,"count":459,"ppm":-2.025463,"heading":null,"cog":null,"speed":null,"to_bow":0,"to_stern":0,"to_starboard":0,"to_port":0,"shiptype":0,"msg_type":0,"country":"US","status":15,"callsign":"","shipname":"16","destination":"","last_signal":6},{"mmsi":367517140,"lat":42.349873,"lon":-71.039650,"distance":1.747478,"mmsi_type":2,"level":-48.541676,"count":124,"ppm":-3.182870,"heading":null,"cog":80.000000,"speed":0.000000,"to_bow":8,"to_stern":13,"to_starboard":3,"to_port":3,"shiptype":30,"msg_type":0,"country":"US","status":15,"callsign":"WDG2585","shipname":"F/V ATLANTIC PRINCE","destination":"","last_signal":7},{"mmsi":367513040,"lat":42.379982,"lon":-71.042534,"distance":0.294650,"mmsi_type":1,"level":-9.986825,"count":6958,"ppm":5.208333,"heading":84,"cog":185.900009,"speed":0.000000,"to_bow":13,"to_stern":13,"to_starboard":0,"to_port":10,"shiptype":52,"msg_type":0,"country":"US","status":15,"callsign":"WDG2187","shipname":"LIBERTY","destination":"BOSTON","last_signal":8},{"mmsi":993672304,"lat":42.261742,"lon":-70.920067,"distance":8.717881,"mmsi_type":6,"level":-44.445862,"count":495,"ppm":-0.578704,"heading":null,"cog":null,"speed":null,"to_bow":0,"to_stern":0,"to_starboard":0,"to_port":0,"shiptype":0,"msg_type":0,"country":"US","status":15,"callsign":"","shipname":"7","destination":"","last_signal":9},{"mmsi":367164250,"lat":42.388348,"lon":-71.063316,"distance":1.336469,"mmsi_type":1,"level":-49.309479,"count":6738,"ppm":-0.578704,"heading":null,"cog":255.300003,"speed":0.000000,"to_bow":10,"to_stern":18,"to_starboard":5,"to_port":5,"shiptype":52,"msg_type":0,"country":"US","status":0,"callsign":"WDD5825","shipname":"FREEDOM","destination":"BOSTON","last_signal":9},{"mmsi":367705350,"lat":42.350880,"lon":-71.038910,"distance":1.684482,"mmsi_type":2,"level":-38.163254,"count":702,"ppm":2.314815,"heading":null,"cog":277.600006,"speed":0.000000,"to_bow":9,"to_stern":18,"to_starboard":3,"to_port":3,"shiptype":30,"msg_type":0,"country":"US","status":15,"callsign":"WDI5118","shipname":"BOOMER TOO","destination":"","last_signal":10},{"mmsi":367659690,"lat":42.361435,"lon":-71.032700,"distance":1.056494,"mmsi_type":1,"level":-31.504950,"count":7026,"ppm":-4.629630,"heading":null,"cog":null,"speed":0.000000,"to_bow":11,"to_stern":11,"to_starboard":4,"to_port":3,"shiptype":8000,"msg_type":0,"country":"US","status":0,"callsign":"WDH412","shipname":"FORTPOINT","destination":"","last_signal":12},{"mmsi":367507210,"lat":42.362240,"lon":-71.026703,"distance":1.080660,"mmsi_type":2,"level":-30.773972,"count":748,"ppm":-0.578704,"heading":195,"cog":334.000000,"speed":0.000000,"to_bow":10,"to_stern":14,"to_starboard":6,"to_port":2,"shiptype":51,"msg_type":0,"country":"US","status":15,"callsign":"M-31","shipname":"AMERICAN UNITED","destination":"","last_signal":12},{"mmsi":993672299,"lat":42.265202,"lon":-70.924660,"distance":8.429752,"mmsi_type":6,"level":-44.418564,"count":415,"ppm":-0.289352,"heading":null,"cog":null,"speed":null,"to_bow":0,"to_stern":0,"to_starboard":0,"to_port":0,"shiptype":0,"msg_type":0,"country":"US","status":15,"callsign":"","shipname":"3","destination":"","last_signal":13},{"mmsi":367513010,"lat":42.388634,"lon":-71.064835,"distance":1.404771,"mmsi_type":1,"level":-44.202557,"count":7352,"ppm":0.000000,"heading":5,"cog":9.400001,"speed":0.000000,"to_bow":12,"to_stern":18,"to_starboard":4,"to_port":6,"shiptype":52,"msg_type":0,"country":"US","status":15,"callsign":"WDG2184","shipname":"JUSTICE","destination":"USBOS<>USBOS","last_signal":14},{"mmsi":367062890,"lat":42.388752,"lon":-71.065216,"distance":1.423112,"mmsi_type":1,"level":-46.292671,"count":336,"ppm":-1.157407,"heading":null,"cog":null,"speed":0.000000,"to_bow":2,"to_stern":11,"to_starboard":2,"to_port":2,"shiptype":53,"msg_type":0,"country":"US","status":0,"callsign":"WDC6899","shipname":"ANNA R","destination":"LINES&STORES","last_signal":15},{"mmsi":367608380,"lat":42.351879,"lon":-71.038101,"distance":1.622244,"mmsi_type":2,"level":-46.738049,"count":21,"ppm":-2.893518,"heading":null,"cog":143.300003,"speed":0.000000,"to_bow":5,"to_stern":15,"to_starboard":1,"to_port":5,"shiptype":30,"msg_type":0,"country":"US","status":15,"callsign":"WDH3543","shipname":"F/V PADRE PIO","destination":"","last_signal":18},{"mmsi":993672290,"lat":42.251125,"lon":-70.954018,"distance":8.492303,"mmsi_type":6,"level":-45.636738,"count":413,"ppm":0.289352,"heading":null,"cog":null,"speed":null,"to_bow":0,"to_stern":0,"to_starboard":0,"to_port":0,"shiptype":0,"msg_type":0,"country":"US","status":15,"callsign":"","shipname":"26","destination":"","last_signal":18},{"mmsi":993672296,"lat":42.254398,"lon":-70.978493,"distance":7.899475,"mmsi_type":6,"level":-44.491932,"count":466,"ppm":-0.289352,"heading":null,"cog":null,"speed":null,"to_bow":0,"to_stern":0,"to_starboard":0,"to_port":0,"shiptype":0,"msg_type":0,"country":"US","status":15,"callsign":"","shipname":"11","destination":"","last_signal":25},{"mmsi":367110280,"lat":42.244095,"lon":-70.970802,"distance":8.596466,"mmsi_type":1,"level":-47.500393,"count":4001,"ppm":3.761574,"heading":null,"cog":null,"speed":0.000000,"to_bow":4,"to_stern":17,"to_starboard":4,"to_port":4,"shiptype":52,"msg_type":0,"country":"US","status":0,"callsign":"WDD2051","shipname":"JAY MICHAEL","destination":"QUINCY","last_signal":26},{"mmsi":993672286,"lat":42.269936,"lon":-70.932907,"distance":7.985576,"mmsi_type":6,"level":-45.610092,"count":437,"ppm":-0.289352,"heading":null,"cog":null,"speed":null,"to_bow":0,"to_stern":0,"to_starboard":0,"to_port":0,"shiptype":0,"msg_type":0,"country":"US","status":15,"callsign":"","shipname":"14","destination":"","last_signal":34},{"mmsi":338397489,"lat":42.381615,"lon":-70.993591,"distance":1.891895,"mmsi_type":2,"level":-37.720192,"count":737,"ppm":-3.761574,"heading":null,"cog":null,"speed":0.000000,"to_bow":6,"to_stern":6,"to_starboard":1,"to_port":2,"shiptype":36,"msg_type":0,"country":"US","status":15,"callsign":"","shipname":"CORVUS","destination":"","last_signal":35},{"mmsi":993672289,"lat":42.255013,"lon":-70.945000,"distance":8.465830,"mmsi_type":6,"level":-44.207458,"count":469,"ppm":-0.868056,"heading":null,"cog":null,"speed":null,"to_bow":0,"to_stern":0,"to_starboard":0,"to_port":0,"shiptype":0,"msg_type":0,"country":"US","status":15,"callsign":"","shipname":"22","destination":"","last_signal":37},{"mmsi":367341190,"lat":42.377220,"lon":-70.884567,"distance":6.722244,"mmsi_type":1,"level":-48.035526,"count":2702,"ppm":-0.868056,"heading":69,"cog":72.599998,"speed":9.700000,"to_bow":15,"to_stern":15,"to_starboard":6,"to_port":6,"shiptype":57,"msg_type":0,"country":"US","status":11,"callsign":"WDE3583","shipname":"WYE RIVER","destination":"USNYC","last_signal":39},{"mmsi":993672288,"lat":42.256687,"lon":-70.941505,"distance":8.453588,"mmsi_type":6,"level":-44.283970,"count":454,"ppm":-0.578704,"heading":null,"cog":null,"speed":null,"to_bow":0,"to_stern":0,"to_starboard":0,"to_port":0,"shiptype":0,"msg_type":0,"country":"US","status":15,"callsign":"","shipname":"19","destination":"","last_signal":41},{"mmsi":993672674,"lat":42.280388,"lon":-70.930878,"distance":7.535347,"mmsi_type":6,"level":-45.412956,"count":464,"ppm":-1.157407,"heading":null,"cog":null,"speed":null,"to_bow":0,"to_stern":0,"to_starboard":0,"to_port":0,"shiptype":0,"msg_type":0,"country":"US","status":15,"callsign":"","shipname":"11","destination":"","last_signal":42},{"mmsi":367110550,"lat":42.246754,"lon":-70.966759,"distance":8.509589,"mmsi_type":1,"level":-47.868286,"count":2446,"ppm":4.629630,"heading":null,"cog":169.900009,"speed":0.000000,"to_bow":10,"to_stern":22,"to_starboard":5,"to_port":4,"shiptype":69,"msg_type":0,"country":"US","status":0,"callsign":"WDJ7743","shipname":"JAMES K GOODWIN","destination":"QUINCY MA","last_signal":43},{"mmsi":367393670,"lat":42.350407,"lon":-71.039238,"distance":1.713944,"mmsi_type":2,"level":-34.527634,"count":736,"ppm":-3.472222,"heading":null,"cog":79.400002,"speed":0.000000,"to_bow":5,"to_stern":17,"to_starboard":1,"to_port":6,"shiptype":30,"msg_type":0,"country":"US","status":15,"callsign":"WDE7469","shipname":"F/V GUARDIAN","destination":"","last_signal":44},{"mmsi":993672281,"lat":42.277458,"lon":-70.932175,"distance":7.639351,"mmsi_type":6,"level":-45.639320,"count":452,"ppm":-0.868056,"heading":null,"cog":null,"speed":null,"to_bow":0,"to_stern":0,"to_starboard":0,"to_port":0,"shiptype":0,"msg_type":0,"country":"US","status":15,"callsign":"","shipname":"WW","destination":"","last_signal":46},{"mmsi":993672675,"lat":42.280941,"lon":-70.932549,"distance":7.463379,"mmsi_type":6,"level":-45.204346,"count":444,"ppm":-0.289352,"heading":null,"cog":null,"speed":null,"to_bow":0,"to_stern":0,"to_starboard":0,"to_port":0,"shiptype":0,"msg_type":0,"country":"US","status":15,"callsign":"","shipname":"10","destination":"","last_signal":50},{"mmsi":366832740,"lat":42.396561,"lon":-71.012863,"distance":1.480322,"mmsi_type":1,"level":-39.069408,"count":652,"ppm":-1.736111,"heading":62,"cog":60.500000,"speed":0.000000,"to_bow":144,"to_stern":28,"to_starboard":15,"to_port":8,"shiptype":12,"msg_type":0,"country":"US","status":5,"callsign":"WDA6472","shipname":"CHRISTIAN REINAUER","destination":"US BOS","last_signal":51},{"mmsi":993672285,"lat":42.273193,"lon":-70.931702,"distance":7.857500,"mmsi_type":6,"level":-44.249130,"count":443,"ppm":-0.578704,"heading":null,"cog":null,"speed":null,"to_bow":0,"to_stern":0,"to_starboard":0,"to_port":0,"shiptype":0,"msg_type":0,"country":"US","status":15,"callsign":"","shipname":"12","destination":"","last_signal":53},{"mmsi":993672284,"lat":42.284195,"lon":-70.929794,"distance":7.387823,"mmsi_type":6,"level":-45.535946,"count":467,"ppm":-0.578704,"heading":null,"cog":null,"speed":null,"to_bow":0,"to_stern":0,"to_starboard":0,"to_port":0,"shiptype":0,"msg_type":0,"country":"US","status":15,"callsign":"","shipname":"9","destination":"","last_signal":54},{"mmsi":368102530,"lat":42.352108,"lon":-71.037971,"distance":1.608208,"mmsi_type":2,"level":-28.080469,"count":403,"ppm":0.289352,"heading":null,"cog":8.600000,"speed":0.000000,"to_bow":8,"to_stern":20,"to_starboard":5,"to_port":5,"shiptype":30,"msg_type":0,"country":"US","status":15,"callsign":"WDK9319","shipname":"FRANCIS DAWN","destination":"","last_signal":65},{"mmsi":993672283,"lat":42.294205,"lon":-70.925056,"distance":7.080395,"mmsi_type":6,"level":-44.212307,"count":473,"ppm":-0.868056,"heading":null,"cog":null,"speed":null,"to_bow":0,"to_stern":0,"to_starboard":0,"to_port":0,"shiptype":0,"msg_type":0,"country":"US","status":15,"callsign":"","shipname":"6","destination":"","last_signal":73},{"mmsi":993672075,"lat":42.336895,"lon":-70.979652,"distance":3.552177,"mmsi_type":6,"level":-45.646450,"count":429,"ppm":-1.446759,"heading":null,"cog":null,"speed":null,"to_bow":0,"to_stern":0,"to_starboard":0,"to_port":0,"shiptype":0,"msg_type":0,"country":"US","status":15,"callsign":"","shipname":"E","destination":"","last_signal":74},{"mmsi":993672102,"lat":42.297688,"lon":-70.923462,"distance":6.982156,"mmsi_type":6,"level":-44.358688,"count":394,"ppm":-0.289352,"heading":null,"cog":null,"speed":null,"to_bow":0,"to_stern":0,"to_starboard":0,"to_port":0,"shiptype":0,"msg_type":0,"country":"US","status":15,"callsign":"","shipname":"4","destination":"","last_signal":77},{"mmsi":993672067,"lat":42.345005,"lon":-71.011528,"distance":2.306010,"mmsi_type":6,"level":-44.231564,"count":445,"ppm":-0.578704,"heading":null,"cog":null,"speed":null,"to_bow":0,"to_stern":0,"to_starboard":0,"to_port":0,"shiptype":0,"msg_type":0,"country":"US","status":15,"callsign":"","shipname":"10","destination":"","last_signal":85},{"mmsi":993672072,"lat":42.345268,"lon":-70.963997,"distance":3.781183,"mmsi_type":6,"level":-45.450157,"count":452,"ppm":-0.289352,"heading":null,"cog":null,"speed":null,"to_bow":0,"to_stern":0,"to_starboard":0,"to_port":0,"shiptype":0,"msg_type":0,"country":"US","status":15,"callsign":"","shipname":"B","destination":"","last_signal":86},{"mmsi":993672071,"lat":42.343204,"lon":-70.959389,"distance":4.020319,"mmsi_type":6,"level":-45.418102,"count":471,"ppm":-1.446759,"heading":null,"cog":null,"speed":null,"to_bow":0,"to_stern":0,"to_starboard":0,"to_port":0,"shiptype":0,"msg_type":0,"country":"US","status":15,"callsign":"","shipname":"A","destination":"","last_signal":90},{"mmsi":993672074,"lat":42.342461,"lon":-70.980843,"distance":3.283750,"mmsi_type":6,"level":-44.312977,"count":425,"ppm":-0.578704,"heading":null,"cog":null,"speed":null,"to_bow":0,"to_stern":0,"to_starboard":0,"to_port":0,"shiptype":0,"msg_type":0,"country":"US","status":15,"callsign":"","shipname":"D","destination":"","last_signal":93},{"mmsi":993672073,"lat":42.344139,"lon":-70.971909,"distance":3.528880,"mmsi_type":6,"level":-44.363037,"count":458,"ppm":-0.578704,"heading":null,"cog":null,"speed":null,"to_bow":0,"to_stern":0,"to_starboard":0,"to_port":0,"shiptype":0,"msg_type":0,"country":"US","status":15,"callsign":"","shipname":"C","destination":"","last_signal":97},{"mmsi":993672841,"lat":42.369629,"lon":-70.919273,"distance":5.211602,"mmsi_type":6,"level":-45.561005,"count":437,"ppm":-1.446759,"heading":null,"cog":null,"speed":null,"to_bow":0,"to_stern":0,"to_starboard":0,"to_port":0,"shiptype":0,"msg_type":0,"country":"US","status":15,"callsign":"","shipname":"2","destination":"","last_signal":98},{"mmsi":993672151,"lat":42.375587,"lon":-70.904961,"distance":5.820148,"mmsi_type":6,"level":-45.494305,"count":487,"ppm":-0.868056,"heading":null,"cog":null,"speed":null,"to_bow":0,"to_stern":0,"to_starboard":0,"to_port":0,"shiptype":0,"msg_type":0,"country":"US","status":15,"callsign":"","shipname":"NC","destination":"","last_signal":102},{"mmsi":366999970,"lat":42.369099,"lon":-71.051956,"distance":0.916293,"mmsi_type":1,"level":-23.678577,"count":361,"ppm":-4.918982,"heading":null,"cog":131.699997,"speed":0.100000,"to_bow":7,"to_stern":12,"to_starboard":3,"to_port":2,"shiptype":55,"msg_type":0,"country":"US","status":5,"callsign":"NATN","shipname":"CG PENDANT","destination":"","last_signal":104},{"mmsi":993672146,"lat":42.202106,"lon":-70.697037,"distance":18.426731,"mmsi_type":6,"level":-45.171604,"count":448,"ppm":-0.578704,"heading":null,"cog":null,"speed":null,"to_bow":0,"to_stern":0,"to_starboard":0,"to_port":0,"shiptype":0,"msg_type":0,"country":"US","status":15,"callsign":"","shipname":"SA","destination":"","last_signal":106},{"mmsi":367615560,"lat":42.384254,"lon":-71.063210,"distance":1.246907,"mmsi_type":1,"level":-33.172131,"count":557,"ppm":-2.604167,"heading":null,"cog":304.700012,"speed":0.000000,"to_bow":12,"to_stern":34,"to_starboard":4,"to_port":7,"shiptype":0,"msg_type":0,"country":"US","status":5,"callsign":"WDH4232","shipname":"WARREN JR","destination":"NEG DWP","last_signal":107},{"mmsi":993672145,"lat":42.390793,"lon":-70.858070,"distance":7.928732,"mmsi_type":6,"level":-45.228577,"count":490,"ppm":-0.578704,"heading":null,"cog":null,"speed":null,"to_bow":0,"to_stern":0,"to_starboard":0,"to_port":0,"shiptype":0,"msg_type":0,"country":"US","status":15,"callsign":"","shipname":"BG","destination":"","last_signal":114},{"mmsi":367361050,"lat":42.380402,"lon":-71.047256,"distance":0.504884,"mmsi_type":1,"level":-23.486078,"count":561,"ppm":-1.446759,"heading":8,"cog":307.600006,"speed":0.000000,"to_bow":10,"to_stern":12,"to_starboard":4,"to_port":3,"shiptype":90,"msg_type":0,"country":"US","status":5,"callsign":"WDH2160","shipname":"AEGEAN SEA","destination":"BOSTON","last_signal":118},{"mmsi":993672305,"lat":42.258495,"lon":-70.918640,"distance":8.912912,"mmsi_type":6,"level":-45.396805,"count":474,"ppm":0.289352,"heading":null,"cog":null,"speed":null,"to_bow":0,"to_stern":0,"to_starboard":0,"to_port":0,"shiptype":0,"msg_type":0,"country":"US","status":15,"callsign":"","shipname":"8","destination":"","last_signal":118},{"mmsi":338377767,"lat":42.381615,"lon":-70.994141,"distance":1.867621,"mmsi_type":2,"level":-36.523090,"count":740,"ppm":0.000000,"heading":null,"cog":null,"speed":0.000000,"to_bow":12,"to_stern":1,"to_starboard":3,"to_port":1,"shiptype":37,"msg_type":0,"country":"US","status":15,"callsign":"FINN","shipname":"FINN","destination":"","last_signal":122},{"mmsi":993672302,"lat":42.264561,"lon":-70.923805,"distance":8.483202,"mmsi_type":6,"level":-45.435638,"count":463,"ppm":-0.868056,"heading":null,"cog":null,"speed":null,"to_bow":0,"to_stern":0,"to_starboard":0,"to_port":0,"shiptype":0,"msg_type":0,"country":"US","status":15,"callsign":"","shipname":"4","destination":"","last_signal":122},{"mmsi":993672065,"lat":42.378387,"lon":-70.782829,"distance":11.235087,"mmsi_type":6,"level":-44.436230,"count":483,"ppm":-0.289352,"heading":null,"cog":null,"speed":null,"to_bow":0,"to_stern":0,"to_starboard":0,"to_port":0,"shiptype":0,"msg_type":0,"country":"US","status":15,"callsign":"","shipname":"B","destination":"","last_signal":125},{"mmsi":338429455,"lat":42.369678,"lon":-71.059860,"distance":1.190502,"mmsi_type":2,"level":-36.182289,"count":740,"ppm":-2.025463,"heading":null,"cog":358.399994,"speed":0.000000,"to_bow":0,"to_stern":15,"to_starboard":2,"to_port":3,"shiptype":37,"msg_type":0,"country":"US","status":15,"callsign":"","shipname":"ANIRAM","destination":"","last_signal":135},{"mmsi":993672293,"lat":42.250637,"lon":-70.971359,"distance":8.218904,"mmsi_type":6,"level":-45.534531,"count":489,"ppm":-1.157407,"heading":null,"cog":null,"speed":null,"to_bow":0,"to_stern":0,"to_starboard":0,"to_port":0,"shiptype":0,"msg_type":0,"country":"US","status":15,"callsign":"","shipname":"4","destination":"","last_signal":138},{"mmsi":993672303,"lat":42.262314,"lon":-70.921249,"distance":8.659142,"mmsi_type":6,"level":-44.015076,"count":469,"ppm":-0.578704,"heading":null,"cog":null,"speed":null,"to_bow":0,"to_stern":0,"to_starboard":0,"to_port":0,"shiptype":0,"msg_type":0,"country":"US","status":15,"callsign":"","shipname":"6","destination":"","last_signal":141},{"mmsi":993672294,"lat":42.252720,"lon":-70.975510,"distance":8.038280,"mmsi_type":6,"level":-44.071507,"count":446,"ppm":-0.868056,"heading":null,"cog":null,"speed":null,"to_bow":0,"to_stern":0,"to_starboard":0,"to_port":0,"shiptype":0,"msg_type":0,"country":"US","status":15,"callsign":"","shipname":"7","destination":"","last_signal":145},{"mmsi":993672295,"lat":42.253841,"lon":-70.976654,"distance":7.957834,"mmsi_type":6,"level":-44.114872,"count":468,"ppm":-0.868056,"heading":null,"cog":null,"speed":null,"to_bow":0,"to_stern":0,"to_starboard":0,"to_port":0,"shiptype":0,"msg_type":0,"country":"US","status":15,"callsign":"","shipname":"9","destination":"","last_signal":149},{"mmsi":993672292,"lat":42.249195,"lon":-70.966637,"distance":8.375034,"mmsi_type":6,"level":-43.899868,"count":414,"ppm":-0.868056,"heading":null,"cog":null,"speed":null,"to_bow":0,"to_stern":0,"to_starboard":0,"to_port":0,"shiptype":0,"msg_type":0,"country":"US","status":15,"callsign":"","shipname":"2","destination":"","last_signal":157},{"mmsi":367784260,"lat":42.375381,"lon":-71.048553,"distance":0.591625,"mmsi_type":2,"level":-48.588799,"count":194,"ppm":-4.340278,"heading":null,"cog":122.300003,"speed":0.000000,"to_bow":0,"to_stern":0,"to_starboard":0,"to_port":0,"shiptype":36,"msg_type":0,"country":"US","status":15,"callsign":"WDJ5096","shipname":"KE GARNE","destination":"","last_signal":170},{"mmsi":371587000,"lat":42.388615,"lon":-71.063187,"distance":1.338217,"mmsi_type":1,"level":-33.425339,"count":898,"ppm":-4.050926,"heading":280,"cog":162.900009,"speed":0.000000,"to_bow":162,"to_stern":28,"to_starboard":10,"to_port":22,"shiptype":70,"msg_type":0,"country":"PA","status":5,"callsign":"3FXC","shipname":"KING BATON ROUGE","destination":"US BOS","last_signal":175},{"mmsi":338331047,"lat":42.361713,"lon":-71.035683,"distance":1.029266,"mmsi_type":2,"level":-36.761642,"count":385,"ppm":0.000000,"heading":null,"cog":320.600006,"speed":0.000000,"to_bow":14,"to_stern":0,"to_starboard":2,"to_port":2,"shiptype":36,"msg_type":0,"country":"US","status":15,"callsign":"","shipname":"RUBICON","destination":"","last_signal":187},{"mmsi":993672291,"lat":42.248093,"lon":-70.961975,"distance":8.514488,"mmsi_type":6,"level":-43.681534,"count":477,"ppm":-0.578704,"heading":null,"cog":null,"speed":null,"to_bow":0,"to_stern":0,"to_starboard":0,"to_port":0,"shiptype":0,"msg_type":0,"country":"US","status":15,"callsign":"","shipname":"28","destination":"","last_signal":189},{"mmsi":993672287,"lat":42.262058,"lon":-70.939133,"distance":8.229729,"mmsi_type":6,"level":-44.021999,"count":456,"ppm":-0.868056,"heading":null,"cog":null,"speed":null,"to_bow":0,"to_stern":0,"to_starboard":0,"to_port":0,"shiptype":0,"msg_type":0,"country":"US","status":15,"callsign":"","shipname":"18","destination":"","last_signal":205},{"mmsi":538006058,"lat":42.386238,"lon":-71.036797,"distance":0.444932,"mmsi_type":1,"level":-8.653960,"count":563,"ppm":-1.157407,"heading":286,"cog":308.600006,"speed":0.000000,"to_bow":169,"to_stern":30,"to_starboard":20,"to_port":12,"shiptype":70,"msg_type":0,"country":"MH","status":5,"callsign":"V7JJ2","shipname":"CLIPPER KYTHIRA","destination":"US BOS","last_signal":226},{"mmsi":993672282,"lat":42.302345,"lon":-70.925163,"distance":6.734277,"mmsi_type":6,"level":-44.285530,"count":439,"ppm":-0.578704,"heading":null,"cog":null,"speed":null,"to_bow":0,"to_stern":0,"to_starboard":0,"to_port":0,"shiptype":0,"msg_type":0,"country":"US","status":15,"callsign":"","shipname":"2","destination":"","last_signal":241},{"mmsi":993672842,"lat":42.368027,"lon":-70.915421,"distance":5.392425,"mmsi_type":6,"level":-44.865604,"count":468,"ppm":-0.578704,"heading":null,"cog":null,"speed":null,"to_bow":0,"to_stern":0,"to_starboard":0,"to_port":0,"shiptype":0,"msg_type":0,"country":"US","status":15,"callsign":"","shipname":"3","destination":"","last_signal":254},{"mmsi":369914081,"lat":42.372555,"lon":-71.056763,"distance":0.992776,"mmsi_type":2,"level":-43.731228,"count":577,"ppm":-0.578704,"heading":null,"cog":null,"speed":0.000000,"to_bow":14,"to_stern":49,"to_starboard":7,"to_port":7,"shiptype":36,"msg_type":0,"country":"US","status":15,"callsign":"","shipname":"USS CONSTITUTION","destination":"","last_signal":278},{"mmsi":366839940,"lat":42.351570,"lon":-71.038383,"distance":1.641508,"mmsi_type":2,"level":-45.525539,"count":342,"ppm":2.025463,"heading":null,"cog":337.200012,"speed":0.000000,"to_bow":14,"to_stern":14,"to_starboard":2,"to_port":5,"shiptype":30,"msg_type":0,"country":"US","status":15,"callsign":"WDA7127","shipname":"F/V AMERICA","destination":"","last_signal":531},{"mmsi":367367470,"lat":42.264828,"lon":-70.921371,"distance":8.534279,"mmsi_type":1,"level":-47.700966,"count":261,"ppm":-0.578704,"heading":128,"cog":125.300003,"speed":5.600000,"to_bow":null,"to_stern":null,"to_starboard":null,"to_port":null,"shiptype":0,"msg_type":0,"country":"US","status":0,"callsign":"","shipname":"","destination":"","last_signal":1022},{"mmsi":314147000,"lat":42.412361,"lon":-70.777626,"distance":11.638142,"mmsi_type":1,"level":-49.616077,"count":2,"ppm":0.000000,"heading":283,"cog":332.600006,"speed":0.100000,"to_bow":null,"to_stern":null,"to_starboard":null,"to_port":null,"shiptype":0,"msg_type":0,"country":"BB","status":1,"callsign":"","shipname":"","destination":"","last_signal":3108},{"mmsi":368068540,"lat":42.350113,"lon":-71.039452,"distance":1.732321,"mmsi_type":2,"level":-47.405190,"count":84,"ppm":0.578704,"heading":null,"cog":250.900009,"speed":0.000000,"to_bow":7,"to_stern":16,"to_starboard":3,"to_port":4,"shiptype":30,"msg_type":0,"country":"US","status":15,"callsign":"","shipname":"OLYMPIA","destination":"","last_signal":4616},{"mmsi":338433824,"lat":42.363102,"lon":-71.031540,"distance":0.966869,"mmsi_type":2,"level":-50.795376,"count":50,"ppm":-0.868056,"heading":null,"cog":null,"speed":0.000000,"to_bow":0,"to_stern":0,"to_starboard":0,"to_port":0,"shiptype":37,"msg_type":0,"country":"US","status":15,"callsign":"","shipname":"SMR MAVERICK","destination":"","last_signal":6003},{"mmsi":14210474,"lat":42.384541,"lon":-15.135415,"distance":2433.074951,"mmsi_type":0,"level":-52.294846,"count":1,"ppm":-3.182870,"heading":216,"cog":304.300018,"speed":92.800003,"to_bow":null,"to_stern":null,"to_starboard":null,"to_port":null,"shiptype":0,"msg_type":0,"country":"","status":7,"callsign":"","shipname":"","destination":"","last_signal":9395},{"mmsi":368016560,"lat":42.371033,"lon":-71.058571,"distance":1.103095,"mmsi_type":2,"level":-50.152996,"count":13,"ppm":-3.761574,"heading":null,"cog":15.800000,"speed":0.000000,"to_bow":4,"to_stern":8,"to_starboard":3,"to_port":2,"shiptype":37,"msg_type":0,"country":"US","status":15,"callsign":"WDJ8454","shipname":"CATHARINE","destination":"","last_signal":19890},{"mmsi":37698652,"lat":28.405867,"lon":-220.145477,"distance":6228.344238,"mmsi_type":1,"level":-57.887344,"count":1,"ppm":1.736111,"heading":null,"cog":null,"speed":null,"to_bow":null,"to_stern":null,"to_starboard":null,"to_port":null,"shiptype":0,"msg_type":0,"country":"VC","status":15,"callsign":"","shipname":"","destination":"","last_signal":20707},{"mmsi":327493679,"lat":-77.286667,"lon":192.376678,"distance":7960.237793,"mmsi_type":1,"level":-54.733349,"count":1,"ppm":-0.289352,"heading":null,"cog":null,"speed":null,"to_bow":null,"to_stern":null,"to_starboard":null,"to_port":null,"shiptype":0,"msg_type":0,"country":"DO","status":15,"callsign":"","shipname":"","destination":"","last_signal":30694},{"mmsi":368202180,"lat":42.374966,"lon":-71.047768,"distance":0.568902,"mmsi_type":2,"level":-24.106043,"count":263,"ppm":-0.289352,"heading":13,"cog":7.700000,"speed":0.000000,"to_bow":12,"to_stern":0,"to_starboard":1,"to_port":3,"shiptype":36,"msg_type":0,"country":"US","status":15,"callsign":"WDM3973","shipname":"LILIBET","destination":"","last_signal":31194},{"mmsi":368079960,"lat":42.349682,"lon":-71.040016,"distance":1.760428,"mmsi_type":2,"level":-46.435463,"count":226,"ppm":0.000000,"heading":null,"cog":218.300003,"speed":0.500000,"to_bow":6,"to_stern":6,"to_starboard":2,"to_port":2,"shiptype":60,"msg_type":0,"country":"US","status":15,"callsign":"","shipname":"ENCORE II","destination":"","last_signal":32210},{"mmsi":368080050,"lat":42.349701,"lon":-71.040207,"distance":1.760150,"mmsi_type":2,"level":-47.338303,"count":260,"ppm":0.868056,"heading":null,"cog":259.100006,"speed":0.200000,"to_bow":7,"to_stern":7,"to_starboard":2,"to_port":2,"shiptype":60,"msg_type":0,"country":"US","status":15,"callsign":"","shipname":"ENCORE I","destination":"","last_signal":33626},{"mmsi":445777755,"lat":null,"lon":null,"distance": null,"mmsi_type":1,"level":-53.633492,"count":1,"ppm":-1.446759,"heading":null,"cog":null,"speed":null,"to_bow":null,"to_stern":null,"to_starboard":null,"to_port":null,"shiptype":0,"msg_type":0,"country":"KP","status":15,"callsign":"","shipname":"","destination":"","last_signal":40649},{"mmsi":446845567,"lat":28.405867,"lon":-220.145477,"distance":6228.344238,"mmsi_type":1,"level":-57.032310,"count":1,"ppm":0.868056,"heading":null,"cog":null,"speed":null,"to_bow":null,"to_stern":null,"to_starboard":null,"to_port":null,"shiptype":0,"msg_type":0,"country":"","status":15,"callsign":"","shipname":"","destination":"","last_signal":40916},{"mmsi":136770999,"lat":null,"lon":null,"distance": null,"mmsi_type":0,"level":-56.138435,"count":1,"ppm":1.736111,"heading":null,"cog":null,"speed":null,"to_bow":0,"to_stern":254,"to_starboard":0,"to_port":32,"shiptype":0,"msg_type":0,"country":"","status":15,"callsign":"3W+UA<W","shipname":";>D/]","destination":",*91ID1UWR$R)A*X]U 7","last_signal":46107},{"mmsi":338158515,"lat":42.342876,"lon":-71.034798,"distance":2.161160,"mmsi_type":2,"level":-47.444366,"count":43,"ppm":-2.893518,"heading":null,"cog":284.700012,"speed":3.400000,"to_bow":4,"to_stern":4,"to_starboard":2,"to_port":1,"shiptype":37,"msg_type":0,"country":"US","status":15,"callsign":"","shipname":"EASTERN RESPONDER","destination":"","last_signal":48480},{"mmsi":684912363,"lat":null,"lon":null,"distance": null,"mmsi_type":1,"level":-54.590816,"count":1,"ppm":-3.472222,"heading":null,"cog":null,"speed":null,"to_bow":270,"to_stern":346,"to_starboard":42,"to_port":32,"shiptype":217,"msg_type":0,"country":"","status":15,"callsign":"I&$#]]3","shipname":"VKE\\M]_<82FUPGQ'B","destination":"_;B.<?#T-","last_signal":49754},{"mmsi":37464534,"lat":null,"lon":null,"distance": null,"mmsi_type":1,"level":-55.792393,"count":1,"ppm":-2.025463,"heading":null,"cog":null,"speed":null,"to_bow":null,"to_stern":null,"to_starboard":null,"to_port":null,"shiptype":0,"msg_type":0,"country":"PA","status":15,"callsign":"","shipname":"","destination":"","last_signal":55594},{"mmsi":361903225,"lat":null,"lon":null,"distance": null,"mmsi_type":1,"level":-56.737110,"count":1,"ppm":0.868056,"heading":null,"cog":null,"speed":null,"to_bow":null,"to_stern":null,"to_starboard":null,"to_port":null,"shiptype":0,"msg_type":0,"country":"PM","status":15,"callsign":"","shipname":"","destination":"","last_signal":56030},{"mmsi":849260578,"lat":null,"lon":null,"distance": null,"mmsi_type":0,"level":-57.425785,"count":1,"ppm":-1.157407,"heading":null,"cog":null,"speed":null,"to_bow":null,"to_stern":null,"to_starboard":null,"to_port":null,"shiptype":0,"msg_type":0,"country":"","status":15,"callsign":"","shipname":"","destination":"","last_signal":57831},{"mmsi":897208726,"lat":null,"lon":null,"distance": null,"mmsi_type":0,"level":-57.199203,"count":1,"ppm":2.314815,"heading":null,"cog":null,"speed":null,"to_bow":null,"to_stern":null,"to_starboard":null,"to_port":null,"shiptype":0,"msg_type":0,"country":"","status":15,"callsign":"","shipname":"","destination":"","last_signal":63411},{"mmsi":173418704,"lat":-100.583908,"lon":63.912861,"distance":7478.399902,"mmsi_type":0,"level":-56.248646,"count":1,"ppm":-0.578704,"heading":75,"cog":204.699997,"speed":98.400002,"to_bow":390,"to_stern":474,"to_starboard":11,"to_port":51,"shiptype":43,"msg_type":0,"country":"","status":15,"callsign":"","shipname":"VE8V(1SAV_:O[\\7C;]4!","destination":"","last_signal":64421}],"error":false}